<?xml version="1.0" encoding="utf-8" ?>
<dwsync>
<file name="bootstrap-select.js" server="ftp.wajabae.com" local="132328153750000000" remote="132370425600000000" Dst="0" />
<file name="bootstrap-select.min.js" server="ftp.wajabae.com" local="132328153750000000" remote="132370425600000000" Dst="0" />
<file name="bootstrap-select.js.map" server="ftp.wajabae.com" local="132328153750000000" remote="132370425600000000" Dst="0" />
<file name="bootstrap-select.min.js.map" server="ftp.wajabae.com" local="132328153760000000" remote="132370425600000000" Dst="0" />
<file name="select2.full.js" server="ftp.wajabae.com" local="132328153750000000" remote="132370425600000000" Dst="0" />
<file name="select2.full.min.js" server="ftp.wajabae.com" local="132328153750000000" remote="132370425600000000" Dst="0" />
<file name="select2.js" server="ftp.wajabae.com" local="132328153750000000" remote="132370425600000000" Dst="0" />
<file name="select2.min.js" server="ftp.wajabae.com" local="132328153750000000" remote="132370425600000000" Dst="0" />
</dwsync>